openturns/dist_bundle1.py
openturns/simulation.py
openturns/_uncertainty.so
openturns/_experimental.so
openturns/transformation.py
openturns/orthogonalbasis.py
openturns/_NormalityTest.so
openturns/LinearModelTest.py
openturns/_optim.so
openturns/_dist_bundle1.so
openturns/_geom.so
openturns/viewer.py
openturns/_typ.so
openturns/model_process.py
openturns/experimental.py
openturns/analytical.py
openturns/weightedexperiment.py
openturns/solver.py
openturns/_statistics.so
openturns/classification.py
openturns/_solver.so
openturns/metamodel.py
openturns/_iterative_statistics.so
openturns/_DistFunc.so
openturns/NormalityTest.py
openturns/_weightedexperiment.so
openturns/geom.py
openturns/graph.py
openturns/VisualTest.py
openturns/_stattests.so
openturns/_testing.so
openturns/_FittingTest.so
openturns/_HypothesisTest.so
openturns/coupling_tools.py
openturns/_SpecFunc.so
openturns/__init__.py
openturns/_bayesian.so
openturns/_model_process.so
openturns/typ.py
openturns/_experiment.so
openturns/uncertainty.py
openturns/_func.so
openturns/_orthogonalbasis.so
openturns/_metamodel.so
openturns/experiment.py
openturns/_LinearModelTest.so
openturns/common.py
openturns/_base.so
openturns/stattests.py
openturns/_classification.so
openturns/_VisualTest.so
openturns/_algo.so
openturns/_graph.so
openturns/_transformation.so
openturns/iterative_statistics.py
openturns/diff.py
openturns/statistics.py
openturns/_dist_bundle2.so
openturns/HypothesisTest.py
openturns/_diff.so
openturns/_randomvector.so
openturns/SpecFunc.py
openturns/dist_bundle3.py
openturns/_model_copula.so
openturns/testing.py
openturns/bayesian.py
openturns/FittingTest.py
openturns/algo.py
openturns/_analytical.so
openturns/optim.py
openturns/dist_bundle2.py
openturns/DistFunc.py
openturns/dist.py
openturns/base.py
openturns/randomvector.py
openturns/func.py
openturns/model_copula.py
openturns/_dist_bundle3.so
openturns/_common.so
openturns-1.25.dist-info/RECORD
openturns-1.25.dist-info/WHEEL
openturns-1.25.dist-info/METADATA
